LICENSE
MANIFEST.in
README.md
setup.py
tap_google_analytics/__init__.py
tap_google_analytics/client.py
tap_google_analytics/discover.py
tap_google_analytics/ga_cubes.json
tap_google_analytics/reports.py
tap_google_analytics/sync.py
tap_google_analytics.egg-info/PKG-INFO
tap_google_analytics.egg-info/SOURCES.txt
tap_google_analytics.egg-info/dependency_links.txt
tap_google_analytics.egg-info/entry_points.txt
tap_google_analytics.egg-info/requires.txt
tap_google_analytics.egg-info/top_level.txt