Metadata-Version: 2.1
Name: tap-google-analytics
Version: 1.1.2
Summary: Singer.io tap for extracting data
Home-page: http://singer.io
Author: Stitch
License: UNKNOWN
Platform: UNKNOWN
Classifier: Programming Language :: Python :: 3 :: Only
Provides-Extra: test
Provides-Extra: dev
License-File: LICENSE
